setup.py
app/__init__.py
wikidreamspip.egg-info/PKG-INFO
wikidreamspip.egg-info/SOURCES.txt
wikidreamspip.egg-info/dependency_links.txt
wikidreamspip.egg-info/not-zip-safe
wikidreamspip.egg-info/top_level.txt