Metadata-Version: 1.0
Name: wikidreamspip
Version: 0.2
Summary: Pip example
Home-page: http://github.com/WikiDreams/wikidreamspip
Author: Wiki Dreams
Author-email: danielsantosvieiramail@gmail.com
License: MIT
Platform: UNKNOWN
